shuup_checkoutfi/__init__.py
shuup_checkoutfi/_version.py
shuup_checkoutfi/admin_forms.py
shuup_checkoutfi/apps.py
shuup_checkoutfi/checkoutfi.py
shuup_checkoutfi/models.py
shuup_checkoutfi/locale/en/LC_MESSAGES/django.mo
shuup_checkoutfi/locale/en/LC_MESSAGES/django.po
shuup_checkoutfi/locale/fi/LC_MESSAGES/django.mo
shuup_checkoutfi/locale/fi/LC_MESSAGES/django.po
shuup_checkoutfi/locale/sv/LC_MESSAGES/django.mo
shuup_checkoutfi/locale/sv/LC_MESSAGES/django.po
shuup_checkoutfi/migrations/0001_initial.py
shuup_checkoutfi/migrations/0002_update_managers.py
shuup_checkoutfi/migrations/__init__.py
shuup_checkoutfi/templates/shuup/checkoutfi/wizard_form.jinja
shuup_checkoutfi-0.6.2.dist-info/LICENSE.txt
shuup_checkoutfi-0.6.2.dist-info/METADATA
shuup_checkoutfi-0.6.2.dist-info/RECORD
shuup_checkoutfi-0.6.2.dist-info/WHEEL
shuup_checkoutfi-0.6.2.dist-info/entry_points.txt
shuup_checkoutfi-0.6.2.dist-info/top_level.txt
