Metadata-Version: 2.1
Name: shuup-checkoutfi
Version: 0.6.2
Summary: Shuup Checkout.fi Integration
Home-page: UNKNOWN
License: MIT
Keywords: stripe,shuup
Platform: UNKNOWN
Provides-Extra: shuup
Provides-Extra: shuup
Requires-Dist: shuup (<2,>=1); extra == 'shuup'
